stealth_browser_controller/__init__.py
stealth_browser_controller/browser.py
stealth_browser_controller/helpers/__init__.py
stealth_browser_controller/helpers/mouse_controller.py
stealth_browser_controller/helpers/screen_shot.py
stealth_browser_controller/models/__init__.py
stealth_browser_controller/models/element.py
stealth_browser_controller-0.1.8.dist-info/METADATA
stealth_browser_controller-0.1.8.dist-info/WHEEL
stealth_browser_controller-0.1.8.dist-info/top_level.txt
stealth_browser_controller-0.1.8.dist-info/RECORD
