Metadata-Version: 2.1
Name: stealth-browser-controller
Version: 0.1.8
Summary: A stealthy browser automation tool with only screen and mouse
Home-page: https://github.com/sarperavci/stealth-browser-controller
Author: Sarper AVCI
Author-email: sarperavci20@gmail.com
Classifier: Development Status :: 3 - Alpha
Classifier: Intended Audience :: Developers
Classifier: License :: OSI Approved :: MIT License
Classifier: Programming Language :: Python :: 3
Requires-Python: >=3.7
Requires-Dist: pyautogui
Requires-Dist: human-mouse
